lineflow/__init__.py
lineflow/core.py
lineflow/cross_validation.py
lineflow/download.py
lineflow/text.py
lineflow/utils.py
lineflow/datasets/__init__.py
lineflow/datasets/cnn_dailymail.py
lineflow/datasets/commonsenseqa.py
lineflow/datasets/conll2000.py
lineflow/datasets/imdb.py
lineflow/datasets/msr_paraphrase.py
lineflow/datasets/penn_treebank.py
lineflow/datasets/scitldr.py
lineflow/datasets/small_parallel_enja.py
lineflow/datasets/snli.py
lineflow/datasets/squad.py
lineflow/datasets/text_classification.py
lineflow/datasets/wikitext.py
lineflow-0.6.8.dist-info/LICENSE
lineflow-0.6.8.dist-info/METADATA
lineflow-0.6.8.dist-info/WHEEL
lineflow-0.6.8.dist-info/top_level.txt
lineflow-0.6.8.dist-info/RECORD
