Metadata-Version: 2.1
Name: lineflow
Version: 0.6.8
Summary: Lightweight NLP Data Loader for All Deep Learning Frameworks in Python
Home-page: https://github.com/yasufumy/lineflow
Author: Yasufumi Taniguchi
Author-email: yasufumi.taniguchi@gmail.com
License: MIT
Platform: UNKNOWN
Classifier: Programming Language :: Python :: 3.6
Classifier: Programming Language :: Python :: 3.7
Classifier: Programming Language :: Python :: 3.8
Classifier: Programming Language :: Python :: 3.9
License-File: LICENSE
Requires-Dist: arrayfiles
Requires-Dist: gdown
